alexflipnote/__init__.py
alexflipnote/client.py
alexflipnote/enums.py
alexflipnote/errors.py
alexflipnote/http.py
alexflipnote/py.typed
alexflipnote/utils.py
alexflipnote/_types/colour.py
alexflipnote/_types/http.py
alexflipnote/_types/http_endpoint.py
alexflipnote/_types/nft.py
alexflipnote/_types/sillycat.py
alexflipnote/models/__init__.py
alexflipnote/models/colour.py
alexflipnote/models/http.py
alexflipnote/models/image.py
alexflipnote/models/nft.py
alexflipnote/models/py.typed
alexflipnote/models/sillycat.py
alexflipnote_py-4.1.0.dist-info/licenses/LICENSE
alexflipnote_py-4.1.0.dist-info/METADATA
alexflipnote_py-4.1.0.dist-info/WHEEL
alexflipnote_py-4.1.0.dist-info/top_level.txt
alexflipnote_py-4.1.0.dist-info/RECORD
