Metadata-Version: 2.4
Name: alexflipnote.py
Version: 4.1.0
Author: Soheab_
License: Mozilla Public License Version 2.0
Project-URL: homepage, https://github.com/Soheab/alexflipnote.py
Project-URL: documentation, https://github.com/Soheab/alexflipnote.py/blob/master/start-docs.md
Project-URL: repository, https://github.com/Soheab/alexflipnote.py
Project-URL: discord, https://discord.gg/yCzcfju
Keywords: alexflipnote,discord,api,wrapper,discord.py
Classifier: Development Status :: 5 - Production/Stable
Classifier: Natural Language :: English
Classifier: Typing :: Typed
Classifier: License :: OSI Approved :: Mozilla Public License 2.0 (MPL 2.0)
Classifier: Programming Language :: Python :: 3 :: Only
Classifier: Programming Language :: Python :: 3.8
Classifier: Programming Language :: Python :: 3.9
Classifier: Programming Language :: Python :: 3.10
Classifier: Programming Language :: Python :: 3.11
Requires-Python: >=3.8
License-File: LICENSE
Requires-Dist: aiohttp<4.0.0,>=3.7.0
Dynamic: license-file
